pdp_kafka_reader/__init__.py
pdp_kafka_reader/argparser.py
pdp_kafka_reader/avro_utils.py
pdp_kafka_reader/conf.py
pdp_kafka_reader/kafka_reader.py
pdp_kafka_reader/transform.py
pdp_kafka_reader/jars/spark-avro_2.11-2.4.0.cloudera2.jar
pdp_kafka_reader-0.0.5.data/scripts/export-avro-jar
pdp_kafka_reader-0.0.5.data/scripts/kafka-reader
pdp_kafka_reader-0.0.5.dist-info/LICENSE
pdp_kafka_reader-0.0.5.dist-info/METADATA
pdp_kafka_reader-0.0.5.dist-info/WHEEL
pdp_kafka_reader-0.0.5.dist-info/top_level.txt
pdp_kafka_reader-0.0.5.dist-info/RECORD
