Metadata-Version: 2.1
Name: pdp-kafka-reader
Version: 0.0.5
Summary: PDP Kafka package
Home-page: UNKNOWN
Author: Filip Beć
Author-email: filip.bec@porsche.digital
License: UNKNOWN
Platform: UNKNOWN
Classifier: Programming Language :: Python :: 3
Classifier: License :: OSI Approved :: MIT License
Classifier: Operating System :: OS Independent
Requires-Python: >=3.6
License-File: LICENSE
Requires-Dist: fastavro (==1.4.7)
Requires-Dist: pandas (==1.1.5)
Requires-Dist: numpy (==1.19.5)
Requires-Dist: pyarrow (==3.0.0)
Requires-Dist: importlib-resources
